niji/__init__.py
niji/color_modes.py
niji/colors.py
niji/core.py
niji/indexed_colors.py
niji/py.typed
niji/roles.py
niji/styles.py
niji/truecolor.py
niji-0.2.0.dist-info/METADATA
niji-0.2.0.dist-info/WHEEL
niji-0.2.0.dist-info/licenses/LICENSE
niji-0.2.0.dist-info/RECORD
