Metadata-Version: 2.4
Name: niji
Version: 0.2.0
Summary: A library for optimistically and explicitly generating and printing ANSI color and style codes.
Project-URL: Homepage, https://github.com/lilellia/niji
Project-URL: Bug Tracker, https://github.com/lilellia/niji/issues
Author-email: Lily Ellington <lilell_@outlook.com>
License-File: LICENSE
Keywords: ansi,color,cprint,style,terminal
Classifier: Development Status :: 3 - Alpha
Classifier: Intended Audience :: Developers
Classifier: License :: OSI Approved :: MIT License
Classifier: Operating System :: OS Independent
Classifier: Programming Language :: Python :: 3
Classifier: Programming Language :: Python :: 3.10
Classifier: Programming Language :: Python :: 3.11
Classifier: Programming Language :: Python :: 3.12
Classifier: Topic :: Software Development :: Libraries :: Python Modules
Classifier: Topic :: Terminals
Requires-Python: >=3.10
